Metadata-Version: 2.1
Name: odoo13-addon-website-no-crawler
Version: 13.0.1.0.1
Summary: Disables robots.txt for indexing by webcrawlers like Google
Home-page: https://github.com/OCA/website
Author: B-Informed B.V., Odoo Community Association (OCA)
Author-email: support@odoo-community.org
License: AGPL-3
Platform: UNKNOWN
Classifier: Programming Language :: Python
Classifier: Framework :: Odoo
Classifier: License :: OSI Approved :: GNU Affero General Public License v3
Requires-Python: >=3.5
Requires-Dist: odoo (<13.1dev,>=13.0a)
